cwcli/cli.py
celuweb_cli-0.0.1.dist-info/METADATA
celuweb_cli-0.0.1.dist-info/WHEEL
celuweb_cli-0.0.1.dist-info/entry_points.txt
celuweb_cli-0.0.1.dist-info/top_level.txt
celuweb_cli-0.0.1.dist-info/RECORD
