Metadata-Version: 2.1
Name: celuweb-cli
Version: 0.0.1
Requires-Dist: click
